i2c_for_esp32/__init__.py
i2c_for_esp32/wirecrc.py
i2c_for_esp32/wirepacker.py
i2c_for_esp32/wireunpacker.py
i2c_for_esp32-0.4.4.dist-info/licenses/LICENSE
i2c_for_esp32-0.4.4.dist-info/licenses/LICENSE.md
i2c_for_esp32-0.4.4.dist-info/METADATA
i2c_for_esp32-0.4.4.dist-info/WHEEL
i2c_for_esp32-0.4.4.dist-info/top_level.txt
i2c_for_esp32-0.4.4.dist-info/RECORD
